Metadata-Version: 2.1
Name: binencrypt
Version: 2.5
Summary: FILE ENCRYPTION EXEC
Home-page: UNKNOWN
Author: K.A.ISHAN OSHADA
Author-email: <ic31908@gmail.com>
License: UNKNOWN
Keywords: binencrypt.crypter(),encrypt(),binencrypt.crypter_V2(),encrypt(),decrypt()
Platform: UNKNOWN
Classifier: Development Status :: 1 - Planning
Classifier: Intended Audience :: Developers
Classifier: Programming Language :: Python :: 3
Classifier: Operating System :: Unix
Classifier: Operating System :: MacOS :: MacOS X
Classifier: Operating System :: Microsoft :: Windows
